py2mass/__about__.py
py2mass/__init__.py
py2mass/__main__.py
py2mass/confirm_order_of_xsc.py
py2mass/py2mass.py
py2mass/py2mass_process_original_psc.py
py2mass/format_descriptors/psc_format_descriptor.csv
py2mass/format_descriptors/xsc_format_descriptor.csv
py2mass-0.1.5.dist-info/DESCRIPTION.rst
py2mass-0.1.5.dist-info/METADATA
py2mass-0.1.5.dist-info/metadata.json
py2mass-0.1.5.dist-info/RECORD
py2mass-0.1.5.dist-info/top_level.txt
py2mass-0.1.5.dist-info/WHEEL
