Metadata-Version: 2.0
Name: py2mass
Version: 0.1.5
Summary: Py2MASS is used for accessing a locally hosted copy of 2MASS PSC/XSC
Home-page: https://github.com/henryroe/Py2MASS
Author: Henry Roe
Author-email: hroe@hroe.me
License: MIT License
Keywords: 2MASS catalog
Platform: UNKNOWN
Classifier: Development Status :: 4 - Beta
Classifier: Intended Audience :: Science/Research
Classifier: Topic :: Scientific/Engineering :: Astronomy
Classifier: License :: OSI Approved :: MIT License
Classifier: Programming Language :: Python :: 2
Classifier: Programming Language :: Python :: 2.7
Requires-Dist: pandas (>=0.10.1)
Requires-Dist: astropy-helpers (>=1.0.0)
